cdk_cloudformation_datadog_integrations_aws/__init__.py
cdk_cloudformation_datadog_integrations_aws/py.typed
cdk_cloudformation_datadog_integrations_aws/_jsii/__init__.py
cdk_cloudformation_datadog_integrations_aws/_jsii/datadog-integrations-aws@2.4.0-alpha.7.jsii.tgz
cdk_cloudformation_datadog_integrations_aws-2.4.0a7.dist-info/LICENSE
cdk_cloudformation_datadog_integrations_aws-2.4.0a7.dist-info/METADATA
cdk_cloudformation_datadog_integrations_aws-2.4.0a7.dist-info/WHEEL
cdk_cloudformation_datadog_integrations_aws-2.4.0a7.dist-info/top_level.txt
cdk_cloudformation_datadog_integrations_aws-2.4.0a7.dist-info/RECORD
